{"$schema":"https://json-schema.org/draft/2020-12/schema","title":"Oracle Lab P0.1 Reviewed Toolchain","type":"object","additionalProperties":false,"required":["schema_version","trust_mode","fixture_root_sha256","environment","tools"],"properties":{"schema_version":{"const":1},"trust_mode":{"enum":["exact_executables_v1","test_fixture_root_v1"]},"fixture_root_sha256":{"anyOf":[{"type":"null"},{"type":"string","pattern":"^sha256:[0-9a-f]{64}$"}]},"environment":{"type":"object","additionalProperties":false,"required":["home","npm_user_config","npm_global_config","goenv"],"properties":{"home":{"const":"/dev/null"},"npm_user_config":{"const":"/dev/null"},"npm_global_config":{"const":"/etc/oracle-p0-1-empty-npmrc"},"goenv":{"const":"off"}}},"tools":{"type":"array","minItems":2,"maxItems":2,"items":{"type":"object","additionalProperties":false,"required":["name","realpath_sha256","executable_sha256","version_sha256"],"properties":{"name":{"enum":["npm","go"]},"realpath_sha256":{"type":"string","pattern":"^sha256:[0-9a-f]{64}$"},"executable_sha256":{"type":"string","pattern":"^sha256:[0-9a-f]{64}$"},"version_sha256":{"type":"string","pattern":"^sha256:[0-9a-f]{64}$"}}}}},"allOf":[{"if":{"properties":{"trust_mode":{"const":"exact_executables_v1"}}},"then":{"properties":{"fixture_root_sha256":{"type":"null"}}}},{"if":{"properties":{"trust_mode":{"const":"test_fixture_root_v1"}}},"then":{"properties":{"fixture_root_sha256":{"type":"string","pattern":"^sha256:[0-9a-f]{64}$"}}}}]}
